nupyprop/geometry.py
nupyprop/data.py
nupyprop/propagate.cpython-310-x86_64-linux-gnu.so
nupyprop/__init__.py
nupyprop/main.py
nupyprop/__main__.py
nupyprop/models/xc_tau_pn_ckmt_water.ecsv
nupyprop/models/ixc_muon_pn_bdhm_water.ecsv
nupyprop/models/ixc_muon_pn_bdhm_rock.ecsv
nupyprop/models/ixc_tau_pn_bdhm_water.ecsv
nupyprop/models/xc_muon_pn_ckmt_water.ecsv
nupyprop/models/xc_tau_pn_ckmt_rock.ecsv
nupyprop/models/ixc_tau_pn_ckmt_water.ecsv
nupyprop/models/ixc_muon_pn_ckmt_water.ecsv
nupyprop/models/xc_muon_pn_bdhm_rock.ecsv
nupyprop/models/ixc_anti_neutrino_ctw.ecsv
nupyprop/models/beta_muon_pn_bdhm_water.ecsv
nupyprop/models/ixc_tau_pn_bdhm_rock.ecsv
nupyprop/models/ixc_muon_pn_ckmt_rock.ecsv
nupyprop/models/__init__.py
nupyprop/models/beta_tau_pn_ckmt_water.ecsv
nupyprop/models/xc_muon_pn_ckmt_rock.ecsv
nupyprop/models/beta_tau_pn_bdhm_water.ecsv
nupyprop/models/beta_tau_pn_bdhm_rock.ecsv
nupyprop/models/xc_anti_neutrino_ctw.ecsv
nupyprop/models/ixc_neutrino_ctw.ecsv
nupyprop/models/xc_neutrino_ctw.ecsv
nupyprop/models/ixc_tau_pn_ckmt_rock.ecsv
nupyprop/models/models.py
nupyprop/models/xc_tau_pn_bdhm_rock.ecsv
nupyprop/models/xc_muon_pn_bdhm_water.ecsv
nupyprop/models/beta_muon_pn_ckmt_water.ecsv
nupyprop/models/beta_muon_pn_ckmt_rock.ecsv
nupyprop/models/xc_tau_pn_bdhm_water.ecsv
nupyprop/models/beta_tau_pn_ckmt_rock.ecsv
nupyprop/models/beta_muon_pn_bdhm_rock.ecsv
nupyprop/datafiles/__init__.py
nupyprop/datafiles/lookup_tables.h5
nupyprop/scripts/run.py
nupyprop/scripts/__init__.py
nupyprop-1.0.post4.dist-info/METADATA
nupyprop-1.0.post4.dist-info/entry_points.txt
nupyprop-1.0.post4.dist-info/WHEEL
nupyprop-1.0.post4.dist-info/RECORD
nupyprop-1.0.post4.dist-info/top_level.txt
nupyprop.libs/libquadmath-96973f99.so.0.0.0
nupyprop.libs/libgomp-a34b3233.so.1.0.0
nupyprop.libs/libgfortran-040039e1.so.5.0.0
