Metadata-Version: 2.1
Name: nupyprop
Version: 1.0.post4
Summary: A simulator for neutrino propagation through the earth.
Home-page: https://heasarc.gsfc.nasa.gov/docs/nuSpaceSim/
Author: Sameer Patel, Diksha Garg, Mary Hall Reno
Author-email: sameer-patel-1@uiowa.edu, diksha-garg@uiowa.edu, mary-hall-reno@uiowa.edu
Maintainer: Sameer Patel, Diksha Garg
Maintainer-email: sameer-patel-1@uiowa.edu, diksha-garg@uiowa.edu
License: MIT
Keywords: NASA,neutrinos,Simulation
Classifier: Intended Audience :: Science/Research
Classifier: Programming Language :: Fortran
Classifier: Programming Language :: Python :: 3 :: Only
Classifier: Programming Language :: Python :: 3
Classifier: Programming Language :: Python :: 3.8
Classifier: Programming Language :: Python :: 3.9
Classifier: Programming Language :: Python :: 3.10
Requires-Dist: astropy
Requires-Dist: h5py
Requires-Dist: importlib-resources
Requires-Dist: matplotlib
Requires-Dist: numpy (>=1.22)
Requires-Dist: scipy
Requires-Dist: sympy
Requires-Dist: pyyaml
Requires-Dist: tabulate
